skelo/__init__.py
skelo/model/__init__.py
skelo/model/base.py
skelo/model/elo.py
skelo/model/glicko2.py
skelo/utils/__init__.py
skelo/utils/elo_data.py
tests/__init__.py
tests/skelo/__init__.py
tests/skelo/model/__init__.py
tests/skelo/model/test_elo.py
skelo-0.1.5.dist-info/LICENSE
skelo-0.1.5.dist-info/METADATA
skelo-0.1.5.dist-info/WHEEL
skelo-0.1.5.dist-info/top_level.txt
skelo-0.1.5.dist-info/RECORD
