Metadata-Version: 2.1
Name: skelo
Version: 0.1.5
Summary: A scikit-learn interface to the Elo and Glicko2 rating systems
Home-page: https://github.com/mbhynes/skelo
Author: Michael B Hynes
Author-email: mike.hynes.rhymes@gmail.com
Classifier: Programming Language :: Python :: 3
Classifier: License :: OSI Approved :: MIT License
Classifier: Operating System :: OS Independent
Classifier: Topic :: Scientific/Engineering :: Information Analysis
Requires-Python: >=3
License-File: LICENSE
Requires-Dist: numpy
Requires-Dist: scikit-learn
Requires-Dist: pandas
Requires-Dist: glicko2 (>=2)
